SoftwarePilot/AnafiCamera.py
SoftwarePilot/AnafiCameraControls.py
SoftwarePilot/AnafiCameraMedia.py
SoftwarePilot/AnafiController.py
SoftwarePilot/AnafiPiloting.py
SoftwarePilot/AnafiRTH.py
SoftwarePilot/SoftwarePilot.py
SoftwarePilot/SoftwarePilotDocker.py
SoftwarePilot/SoftwarePilotService.py
SoftwarePilot/__init__.py
SoftwarePilot-1.2.6.dist-info/METADATA
SoftwarePilot-1.2.6.dist-info/WHEEL
SoftwarePilot-1.2.6.dist-info/top_level.txt
SoftwarePilot-1.2.6.dist-info/RECORD
