Metadata-Version: 2.1
Name: SoftwarePilot
Version: 1.2.6
Summary: SoftwarePilot is an open source middleware and API that supports aerial applications for Parrot Anafi drones
Home-page: https://github.com/boredbot2/SoftwarePilot
Author: Kevyn Angueira Irizarry
Author-email: kevyn.angueira@gmail.com
License: UNKNOWN
Platform: UNKNOWN
Requires-Python: >=3.6
Requires-Dist: PyOpenGL (>=3.1.6)
Requires-Dist: PySDL2 (>=0.9.12)
Requires-Dist: docker (>=5.0.3)
Requires-Dist: fastapi (>=0.79.0)
Requires-Dist: opencv-python (>=4.6.0.66)
Requires-Dist: parrot-olympe (==7.5.0)
Requires-Dist: python-multipart (>=0.0.5)
Requires-Dist: requests (>=2.22.0)
Requires-Dist: uvicorn (>=0.18.2)
